figure/__init__.py
figure/api_requestor.py
figure/error.py
figure/resource.py
figure_sdk-0.3.2.dist-info/LICENSE
figure_sdk-0.3.2.dist-info/METADATA
figure_sdk-0.3.2.dist-info/WHEEL
figure_sdk-0.3.2.dist-info/top_level.txt
figure_sdk-0.3.2.dist-info/RECORD
